assets/logo.jpg
thundra_io/__init__.py
thundra_io/__main__.py
thundra_io/agents.py
thundra_io/button/__init__.py
thundra_io/button/registry.py
thundra_io/button/types.py
thundra_io/button/v1.py
thundra_io/button/v2.py
thundra_io/chain.py
thundra_io/cli.py
thundra_io/command.py
thundra_io/config.py
thundra_io/core/__init__.py
thundra_io/core/graph.py
thundra_io/core/llm.py
thundra_io/core/memory.py
thundra_io/evaluater.py
thundra_io/middleware.py
thundra_io/plugins.py
thundra_io/profiler/__init__.py
thundra_io/storage/__init__.py
thundra_io/storage/file.py
thundra_io/templates/.gitignore
thundra_io/templates/README.md
thundra_io/templates/app/agents/rebase.py
thundra_io/templates/app/agents/yt.py
thundra_io/templates/app/app.py
thundra_io/templates/app/commands/base.py
thundra_io/templates/app/commands/yt.py
thundra_io/templates/app/middleware/auto_save_media.py
thundra_io/templates/thundra.toml
thundra_io/test.py
thundra_io/types.py
thundra_io/utils.py
thundra_io/workdir.py
thundra_io-0.1.6.dist-info/LICENSE
thundra_io-0.1.6.dist-info/METADATA
thundra_io-0.1.6.dist-info/WHEEL
thundra_io-0.1.6.dist-info/entry_points.txt
thundra_io-0.1.6.dist-info/RECORD
