Metadata-Version: 2.1
Name: thundra-io
Version: 0.1.6
Summary: Neonize Abstraction
Home-page: https://github.com/krypton-byte/thundra
License: Apache 2.0
Keywords: neonize,whatsapp,framework,websocket,bot
Author: krypton-byte
Author-email: rosid6434@gmail.com
Requires-Python: >=3.11,<4.0
Classifier: License :: Other/Proprietary License
Classifier: Programming Language :: Python :: 3
Classifier: Programming Language :: Python :: 3.11
Classifier: Programming Language :: Python :: 3.12
Classifier: Programming Language :: Python :: 3.13
Requires-Dist: appdirs (>=1.4.4,<2.0.0)
Requires-Dist: cachetools (>=5.3.3,<6.0.0)
Requires-Dist: graphviz (>=0.20.1,<0.21.0)
Requires-Dist: langchain (>=0.1.11,<0.2.0)
Requires-Dist: langchain-openai (>=0.0.8,<0.0.9)
Requires-Dist: neonize (>=0.3.1,<0.4.0)
Requires-Dist: pytube (>=15.0.0,<16.0.0)
Requires-Dist: tomli-w (>=1.0.0,<2.0.0)
Project-URL: Repository, https://github.com/krypton-byte/thundra.git
